Metadata-Version: 2.1
Name: metaform
Version: 1.0.0
Summary: A utility for defining metadata for data types and formats.
Home-page: https://gitlab.com/wefindx/metaform
Author: Mindey
Author-email: mindey@qq.com
License: ASK FOR PERMISSIONS
Platform: UNKNOWN
Provides-Extra: test
